.DS_Store
insta_python_api/__init__.py
insta_python_api/apis.py
insta_python_api/config.yaml
insta_python_api/http_requests.py
insta_python_api/main.py
insta_python_api-1.1.0.dist-info/METADATA
insta_python_api-1.1.0.dist-info/WHEEL
insta_python_api-1.1.0.dist-info/top_level.txt
insta_python_api-1.1.0.dist-info/RECORD
