Metadata-Version: 2.1
Name: insta-python-api
Version: 1.1.0
Summary: instafoging python api package
Home-page: https://github.com/allesx/insta_python
Author: xingpeidong
Author-email: xpd1437@126.com
License: MIT
Classifier: Programming Language :: Python :: 3
Requires-Dist: requests
Requires-Dist: PyYAML
